{
	"configurations" : 
	[
		{
			"abstractTargets" : [],
			"directories" : 
			[
				{
					"build" : ".",
					"childIndexes" : 
					[
						1
					],
					"jsonFile" : "directory-.-Debug-9ad1a58d4644cf6543fa.json",
					"minimumCMakeVersion" : 
					{
						"string" : "3.10"
					},
					"projectIndex" : 0,
					"source" : "."
				},
				{
					"build" : "src",
					"childIndexes" : 
					[
						2,
						3
					],
					"jsonFile" : "directory-src-Debug-c61fb49069c3d1aa76de.json",
					"minimumCMakeVersion" : 
					{
						"string" : "3.10"
					},
					"parentIndex" : 0,
					"projectIndex" : 0,
					"source" : "src"
				},
				{
					"build" : "src/server",
					"jsonFile" : "directory-src.server-Debug-a6895045833bd2400808.json",
					"minimumCMakeVersion" : 
					{
						"string" : "3.10"
					},
					"parentIndex" : 1,
					"projectIndex" : 0,
					"source" : "src/server",
					"targetIndexes" : 
					[
						1
					]
				},
				{
					"build" : "src/client",
					"jsonFile" : "directory-src.client-Debug-5bf37a0cd15b9746c489.json",
					"minimumCMakeVersion" : 
					{
						"string" : "3.10"
					},
					"parentIndex" : 1,
					"projectIndex" : 0,
					"source" : "src/client",
					"targetIndexes" : 
					[
						0
					]
				}
			],
			"name" : "Debug",
			"projects" : 
			[
				{
					"directoryIndexes" : 
					[
						0,
						1,
						2,
						3
					],
					"name" : "chat",
					"targetIndexes" : 
					[
						0,
						1
					]
				}
			],
			"targets" : 
			[
				{
					"directoryIndex" : 3,
					"id" : "ChatClient::@8ca63c80a879d0067daa",
					"jsonFile" : "target-ChatClient-Debug-a64164ad0acbdbc04dc2.json",
					"name" : "ChatClient",
					"projectIndex" : 0
				},
				{
					"directoryIndex" : 2,
					"id" : "ChatServer::@2804e40980a64c7d7ad1",
					"jsonFile" : "target-ChatServer-Debug-5910607ab04bcf8918ab.json",
					"name" : "ChatServer",
					"projectIndex" : 0
				}
			]
		}
	],
	"kind" : "codemodel",
	"paths" : 
	{
		"build" : "/home/woshi/chat/build",
		"source" : "/home/woshi/chat"
	},
	"version" : 
	{
		"major" : 2,
		"minor" : 9
	}
}
